pyfireconsole/__init__.py
pyfireconsole/__main__.py
pyfireconsole/console/__init__.py
pyfireconsole/console/pyfireconsole.py
pyfireconsole/console/run_console.py
pyfireconsole/db/__init__.py
pyfireconsole/db/connection.py
pyfireconsole/models/__init__.py
pyfireconsole/models/association.py
pyfireconsole/models/firestore_model.py
pyfireconsole/models/pyfire_model.py
pyfireconsole/queries/__init__.py
pyfireconsole/queries/abstract_query.py
pyfireconsole/queries/all_query.py
pyfireconsole/queries/delete_query.py
pyfireconsole/queries/get_query.py
pyfireconsole/queries/order_query.py
pyfireconsole/queries/query.py
pyfireconsole/queries/query_runner.py
pyfireconsole/queries/save_query.py
pyfireconsole/queries/where_clouse.py
pyfireconsole/queries/where_query.py
pyfireconsole-0.1.1.dist-info/LICENSE
pyfireconsole-0.1.1.dist-info/METADATA
pyfireconsole-0.1.1.dist-info/WHEEL
pyfireconsole-0.1.1.dist-info/entry_points.txt
pyfireconsole-0.1.1.dist-info/top_level.txt
pyfireconsole-0.1.1.dist-info/RECORD
