Metadata-Version: 2.1
Name: pyfireconsole
Version: 0.1.1
Summary: An interactive console for Firestore based on Python ORM
Home-page: https://github.com/tan-z-tan/pyfireconsole
Author: Makoto Tanji
Author-email: tanji.makoto@gmail.com
Classifier: Development Status :: 4 - Beta
Classifier: Environment :: Console
Classifier: Intended Audience :: Developers
Classifier: License :: OSI Approved :: MIT License
Classifier: Programming Language :: Python
Classifier: Programming Language :: Python :: 3
Classifier: Programming Language :: Python :: 3.8
Classifier: Programming Language :: Python :: 3.9
Classifier: Programming Language :: Python :: 3.10
Classifier: Programming Language :: Python :: 3.11
Classifier: Programming Language :: Python :: 3.12
Classifier: Programming Language :: Python :: 3 :: Only
Classifier: Programming Language :: Python :: Implementation :: CPython
Classifier: Programming Language :: Python :: Implementation :: PyPy
Classifier: Topic :: Software Development :: Libraries
Requires-Python: >=3.8.0
License-File: LICENSE
Requires-Dist: google-cloud-firestore (<3.0.0,>=2.0.0)
Requires-Dist: google-auth (<3.0.0,>=2.0.0)
Requires-Dist: inflection (<0.6.0,>=0.5.1)
Requires-Dist: pydantic (<3.0.0,>=2.0.1)
Requires-Dist: ipython (<9.0.0,>=7.0.1)
